db_connection/__init__.py
db_connection/db_connection.py
db_connection/test_db_conn.py
PyDbConnector_Jinghan_Ma-0.0.5.dist-info/LICENSE
PyDbConnector_Jinghan_Ma-0.0.5.dist-info/METADATA
PyDbConnector_Jinghan_Ma-0.0.5.dist-info/WHEEL
PyDbConnector_Jinghan_Ma-0.0.5.dist-info/top_level.txt
PyDbConnector_Jinghan_Ma-0.0.5.dist-info/RECORD
